OneNetAPI
