Metadata-Version: 2.1
Name: OneNetAPI
Version: 0.4
Summary: OneNetAPI API
Home-page: 
Download-URL: 
Author: Jinfang Wei
Author-email: 2295542405@qq.com
License: MIT
Keywords: API,OneNetAPI,Python
Classifier: Development Status :: 3 - Alpha
Classifier: Intended Audience :: Developers
Classifier: Topic :: Software Development :: Build Tools
Classifier: License :: OSI Approved :: MIT License
Classifier: Programming Language :: Python :: 3.7
